{
    "transaction_id": "18-0A5-0C53DF",
    "server_time": 1693041343049,
    "beginner_mission": {
        "is_badge": false,
        "is_display": false
    },
    "main_mission": {
        "currents": [
            "Clear Story Ch. 1"
        ],
        "is_display": true
    },
    "select_history": [],
    "res_code": 0,
    "client_wait": 0,
    "selects": [],
    "names": [],
    "texts": [
        {
            "id": 0,
            "text": "Stats for all the demons you've acquired can be viewed here."
        },
        {
            "id": 1,
            "text": "You can manage the demons you have obtained in your [cus color=emphasis]Inventory[cus color=end] and<BR>[cus color=emphasis]Storage[cus color=end]."
        },
        {
            "id": 2,
            "text": "Press this button to store demons in Storage."
        },
        {
            "id": 3,
            "text": "Don't forget that you won't be able to use the demons in Storage"
        },
        {
            "id": 4,
            "text": "for Fusion and other purposes, so be careful."
        },
        {
            "id": 5,
            "text": "Next, tap on a demon to view its [cus color=emphasis]DEMON INFORMATION[cus color=end]."
        }
    ],
    "tm": "68",
    "comeback_mission": {
        "is_badge": false,
        "is_display": false
    },
    "commands": [
        {
            "voice": "",
            "face": "",
            "select": 0,
            "flag": "",
            "uniq": 3001440,
            "effect": "",
            "param0": "0",
            "place": 0,
            "param3": "",
            "command": 20,
            "param1": "1",
            "param2": ""
        },
        {
            "voice": "",
            "face": "",
            "select": 0,
            "flag": "",
            "uniq": 3001441,
            "effect": "",
            "param0": "tgt_node_1",
            "place": 0,
            "param3": "",
            "command": 17,
            "param1": "tgt_wipe_1",
            "param2": "3"
        },
        {
            "voice": "",
            "face": "",
            "select": 0,
            "flag": "",
            "uniq": 3001442,
            "effect": "",
            "param0": "1",
            "place": 0,
            "param3": "",
            "command": 20,
            "param1": "1",
            "param2": ""
        },
        {
            "voice": "",
            "face": "",
            "select": 0,
            "flag": "",
            "uniq": 3001443,
            "effect": "",
            "param0": "",
            "place": 0,
            "param3": "",
            "command": 18,
            "param1": "",
            "param2": ""
        },
        {
            "voice": "",
            "face": "",
            "select": 0,
            "flag": "",
            "uniq": 3001444,
            "effect": "",
            "param0": "tgt_node_2",
            "place": 0,
            "param3": "",
            "command": 17,
            "param1": "",
            "param2": "0"
        },
        {
            "voice": "",
            "face": "",
            "select": 0,
            "flag": "",
            "uniq": 3001445,
            "effect": "",
            "param0": "2",
            "place": 0,
            "param3": "",
            "command": 20,
            "param1": "1",
            "param2": ""
        },
        {
            "voice": "",
            "face": "",
            "select": 0,
            "flag": "",
            "uniq": 3001446,
            "effect": "",
            "param0": "3",
            "place": 0,
            "param3": "",
            "command": 20,
            "param1": "1",
            "param2": ""
        },
        {
            "voice": "",
            "face": "",
            "select": 0,
            "flag": "",
            "uniq": 3001447,
            "effect": "",
            "param0": "4",
            "place": 0,
            "param3": "",
            "command": 20,
            "param1": "1",
            "param2": ""
        },
        {
            "voice": "",
            "face": "",
            "select": 0,
            "flag": "",
            "uniq": 3001448,
            "effect": "",
            "param0": "",
            "place": 0,
            "param3": "",
            "command": 18,
            "param1": "",
            "param2": ""
        },
        {
            "voice": "",
            "face": "",
            "select": 0,
            "flag": "",
            "uniq": 3001449,
            "effect": "",
            "param0": "5",
            "place": 0,
            "param3": "",
            "command": 20,
            "param1": "1",
            "param2": ""
        },
        {
            "voice": "",
            "face": "",
            "select": 0,
            "flag": "",
            "uniq": 3001450,
            "effect": "",
            "param0": "tgt_node_0",
            "place": 0,
            "param3": "",
            "command": 19,
            "param1": "",
            "param2": ""
        }
    ],
    "charas": []
}