{
  "transaction_id": "19-039-19C476",
  "server_time": 1697840240407,
  "beginner_mission": {
    "is_badge": false,
    "is_display": false
  },
  "main_mission": {
    "currents": [
      "Clear Story Ch. 1"
    ],
    "is_display": true
  },
  "select_history": [],
  "res_code": 0,
  "client_wait": 0,
  "selects": [],
  "gacha_banner_info": {
    "img": "4800000",
    "end_ts": 1699109999000,
    "limited_days": 14
  },
  "names": [
    {
      "name": "Man",
      "id": 1000
    },
    {
      "name": "Woman",
      "id": 1100
    },
    {
      "name": "Woman",
      "id": 1305
    },
    {
      "name": "Rika",
      "id": 120
    },
    {
      "name": "Seiran",
      "id": 250
    },
    {
      "name": "Gakuto",
      "id": 170
    },
    {
      "name": "Dionysus",
      "id": 17100
    }
  ],
  "texts": [
    {
      "id": 0,
      "text": ">Akihabara is in a festive mood."
    },
    {
      "id": 1,
      "text": "Let's drink to nature's bounty!"
    },
    {
      "id": 2,
      "text": "Cheers!"
    },
    {
      "id": 3,
      "text": "...Mmmm, this wine is so good!"
    },
    {
      "id": 4,
      "text": "*Giggle* This is what I call fun! C'mon, let's dance!"
    },
    {
      "id": 5,
      "text": "Alright!"
    },
    {
      "id": 6,
      "text": "...The place really HAS come alive."
    },
    {
      "id": 7,
      "text": "Just like I said right? I was as surprised by this as you are when I saw what was going on."
    },
    {
      "id": 8,
      "text": "I sure picked the right time to come by the Hideout."
    },
    {
      "id": 9,
      "text": "I just LOVE events and festivals."
    },
    {
      "id": 10,
      "text": "So that's why you dragged us out here on your escapade."
    },
    {
      "id": 11,
      "text": "But this is odd. A festival this time of year in Akihabara? ...What is it about anyway?"
    },
    {
      "id": 12,
      "text": "Why don't we ask around."
    },
    {
      "id": 13,
      "text": "Umm, excuse me miss?"
    },
    {
      "id": 14,
      "text": "Things are really lively here today. Is there an event or something?"
    },
    {
      "id": 15,
      "text": "It's a festival to celebrate Dionysus!"
    },
    {
      "id": 16,
      "text": "Dionysus?"
    },
    {
      "id": 17,
      "text": "That's..."
    },
    {
      "id": 18,
      "text": "The god of wine and fertility!"
    },
    {
      "id": 19,
      "text": "So what you're drinking is..."
    },
    {
      "id": 20,
      "text": "Yeah, wine. It's really great..."
    },
    {
      "id": 21,
      "text": "Why don't you guys get some too?"
    },
    {
      "id": 22,
      "text": "They're handing these out for free at the center of the festival grounds!"
    },
    {
      "id": 23,
      "text": "Oh really? That sounds great, we'll go take a look!"
    },
    {
      "id": 24,
      "text": "Weird festival."
    },
    {
      "id": 25,
      "text": "Kinda fishy, don't you think?"
    },
    {
      "id": 26,
      "text": "Not really."
    },
    {
      "id": 27,
      "text": "Dionysus is the god of wine, also called Bacchus by the Romans."
    },
    {
      "id": 28,
      "text": "Some winery must be holding a wine tasting event in his name or something."
    },
    {
      "id": 29,
      "text": "It's just an ad campaign. Fits the Autumn season just fine."
    },
    {
      "id": 30,
      "text": "There there, let's just go and find out okay?"
    },
    {
      "id": 31,
      "text": ">At the center of the festivities..."
    },
    {
      "id": 32,
      "text": "A wine tasting event held by some winery..."
    },
    {
      "id": 33,
      "text": "Boy was I so wrong."
    },
    {
      "id": 34,
      "text": "Lord Dionysus! Bestow upon us your bounty!"
    },
    {
      "id": 35,
      "text": "Lord Dionysus! Can we get some refills here too?"
    },
    {
      "id": 36,
      "text": "Yes, yes. Of course. It is a day of celebration after all!"
    },
    {
      "id": 37,
      "text": "I am the god of bounty... All those who worship me shall benefit!"
    },
    {
      "id": 38,
      "text": "It's a demon!! Why is a demon handing out wine?!"
    },
    {
      "id": 39,
      "text": "What a crowd. I wonder if it's really that delicious..."
    },
    {
      "id": 40,
      "text": "What are you talking about? We gotta stop him!"
    },
    {
      "id": 41,
      "text": "I'm speaking from experience here! NEVER drink something handed to you by a demon!"
    },
    {
      "id": 42,
      "text": "Let's go, Devil Download!"
    },
    {
      "id": 43,
      "text": "!!<BR>What have we here..."
    },
    {
      "id": 44,
      "text": "You there! What's the meaning of this?"
    },
    {
      "id": 45,
      "text": "I see..., You're demon summoners."
    },
    {
      "id": 46,
      "text": "How fortunate. I was hoping to cross paths with ones such as you."
    },
    {
      "id": 47,
      "text": "Umm, what?"
    },
    {
      "id": 48,
      "text": "I have no hostile intentions. Just hear what I have to say."
    },
    {
      "id": 49,
      "text": "...Say what?"
    },
    {
      "id": 50,
      "text": "This is a festival to celebrate the coming of harvest"
    },
    {
      "id": 51,
      "text": "dedicated to me since I am a fertility god."
    },
    {
      "id": 52,
      "text": "Well yeah, but usually this kind of thing is held by the worshippers, not the worshipped..."
    },
    {
      "id": 53,
      "text": "I like to personally bestow the gift of wine upon all those who would join the celebration."
    },
    {
      "id": 54,
      "text": "It's a personal rule of mine. A matter of principle, you see."
    },
    {
      "id": 55,
      "text": "Okayyy..."
    },
    {
      "id": 56,
      "text": "But... More people turned out than expected,"
    },
    {
      "id": 57,
      "text": "and I'm running out of grapes to make wine."
    },
    {
      "id": 58,
      "text": "So I would like to ask you to harvest some for me with you demon-fighting skills."
    },
    {
      "id": 59,
      "text": "...?<BR>What do you mean?"
    },
    {
      "id": 60,
      "text": "I have enveloped this region with my magic."
    },
    {
      "id": 61,
      "text": "So if you kill a demon in this area, their power will be absorbed to become grapes."
    },
    {
      "id": 62,
      "text": "You wield demons, so harvesting grapes should be an easy task for you."
    },
    {
      "id": 63,
      "text": "You're using grapes like that to make the wine?! That's unacceptable...!"
    },
    {
      "id": 64,
      "text": "Yeah, wine made from grapes grown from dead demons?"
    },
    {
      "id": 65,
      "text": "It's gotta be something bad."
    },
    {
      "id": 66,
      "text": "Why do you say that? It's actually pretty good."
    },
    {
      "id": 67,
      "text": "You're drinking it?! You have like zero caution!!"
    },
    {
      "id": 68,
      "text": "As I said, I have enveloped this region with my magic."
    },
    {
      "id": 69,
      "text": "Grapes usually take time to bear fruit,"
    },
    {
      "id": 70,
      "text": "but my powers of fertility, alongside the power taken from demons, can speed up that process."
    },
    {
      "id": 71,
      "text": "There's nothing wrong with the grapes themselves."
    },
    {
      "id": 72,
      "text": "I just want to show those who worship me a good time,"
    },
    {
      "id": 73,
      "text": "so I'm using my powers of fertility to cheat a little, that's all."
    },
    {
      "id": 74,
      "text": "I don't even know what to make of that."
    },
    {
      "id": 75,
      "text": "So anyhow, I thank you for your help."
    },
    {
      "id": 76,
      "text": "Let's make this festival a day to remember!"
    }
  ],
  "tm": "8",
  "comeback_mission": {
    "is_badge": false,
    "is_display": false
  },
  "commands": [
    {
      "voice": "",
      "face": "",
      "select": 0,
      "flag": "",
      "uniq": 6023932,
      "effect": "",
      "param0": "drama_bg_001.png",
      "place": 0,
      "param3": "",
      "command": 1,
      "param1": "",
      "param2": ""
    },
    {
      "voice": "",
      "face": "",
      "select": 0,
      "flag": "",
      "uniq": 6023933,
      "effect": "",
      "param0": "bgm_drama_quiet",
      "place": 0,
      "param3": "",
      "command": 12,
      "param1": "",
      "param2": ""
    },
    {
      "voice": "",
      "face": "",
      "select": 0,
      "flag": "",
      "uniq": 6023934,
      "effect": "",
      "param0": "0",
      "place": 0,
      "param3": "",
      "command": 4,
      "param1": "",
      "param2": ""
    },
    {
      "voice": "",
      "face": "idle",
      "select": 0,
      "flag": "",
      "uniq": 6023935,
      "effect": "",
      "param0": "1",
      "place": 0,
      "param3": "",
      "command": 2,
      "param1": "1000",
      "param2": ""
    },
    {
      "voice": "",
      "face": "idle",
      "select": 0,
      "flag": "",
      "uniq": 6023936,
      "effect": "",
      "param0": "2",
      "place": 1,
      "param3": "",
      "command": 2,
      "param1": "1100",
      "param2": ""
    },
    {
      "voice": "",
      "face": "idle",
      "select": 0,
      "flag": "",
      "uniq": 6023937,
      "effect": "",
      "param0": "3",
      "place": 0,
      "param3": "",
      "command": 2,
      "param1": "1305",
      "param2": ""
    },
    {
      "voice": "",
      "face": "idle",
      "select": 0,
      "flag": "",
      "uniq": 6023938,
      "effect": "",
      "param0": "4",
      "place": 1,
      "param3": "",
      "command": 2,
      "param1": "1100",
      "param2": ""
    },
    {
      "voice": "",
      "face": "idle",
      "select": 0,
      "flag": "",
      "uniq": 6023939,
      "effect": "",
      "param0": "5",
      "place": 0,
      "param3": "",
      "command": 2,
      "param1": "1000",
      "param2": ""
    },
    {
      "voice": "",
      "face": "",
      "select": 0,
      "flag": "",
      "uniq": 6023940,
      "effect": "",
      "param0": "all",
      "place": 0,
      "param3": "",
      "command": 3,
      "param1": "",
      "param2": ""
    },
    {
      "voice": "",
      "face": "idle",
      "select": 0,
      "flag": "",
      "uniq": 6023941,
      "effect": "",
      "param0": "6",
      "place": 0,
      "param3": "",
      "command": 2,
      "param1": "120",
      "param2": ""
    },
    {
      "voice": "",
      "face": "idle",
      "select": 0,
      "flag": "",
      "uniq": 6023942,
      "effect": "",
      "param0": "7",
      "place": 1,
      "param3": "",
      "command": 2,
      "param1": "250",
      "param2": ""
    },
    {
      "voice": "",
      "face": "idle",
      "select": 0,
      "flag": "",
      "uniq": 6023943,
      "effect": "",
      "param0": "8",
      "place": 1,
      "param3": "",
      "command": 2,
      "param1": "250",
      "param2": ""
    },
    {
      "voice": "",
      "face": "face_01",
      "select": 0,
      "flag": "",
      "uniq": 6023944,
      "effect": "",
      "param0": "9",
      "place": 1,
      "param3": "",
      "command": 2,
      "param1": "250",
      "param2": ""
    },
    {
      "voice": "",
      "face": "idle",
      "select": 0,
      "flag": "",
      "uniq": 6023945,
      "effect": "",
      "param0": "10",
      "place": 0,
      "param3": "",
      "command": 2,
      "param1": "170",
      "param2": ""
    },
    {
      "voice": "",
      "face": "idle",
      "select": 0,
      "flag": "",
      "uniq": 6023946,
      "effect": "",
      "param0": "11",
      "place": 0,
      "param3": "",
      "command": 2,
      "param1": "170",
      "param2": ""
    },
    {
      "voice": "",
      "face": "idle",
      "select": 0,
      "flag": "",
      "uniq": 6023947,
      "effect": "",
      "param0": "12",
      "place": 1,
      "param3": "",
      "command": 2,
      "param1": "250",
      "param2": ""
    },
    {
      "voice": "",
      "face": "idle",
      "select": 0,
      "flag": "",
      "uniq": 6023948,
      "effect": "",
      "param0": "13",
      "place": 1,
      "param3": "",
      "command": 2,
      "param1": "250",
      "param2": ""
    },
    {
      "voice": "",
      "face": "idle",
      "select": 0,
      "flag": "",
      "uniq": 6023949,
      "effect": "",
      "param0": "14",
      "place": 1,
      "param3": "",
      "command": 2,
      "param1": "250",
      "param2": ""
    },
    {
      "voice": "",
      "face": "idle",
      "select": 0,
      "flag": "",
      "uniq": 6023950,
      "effect": "",
      "param0": "15",
      "place": 0,
      "param3": "",
      "command": 2,
      "param1": "1100",
      "param2": ""
    },
    {
      "voice": "",
      "face": "",
      "select": 0,
      "flag": "",
      "uniq": 6023951,
      "effect": "",
      "param0": "16",
      "place": 0,
      "param3": "",
      "command": 6,
      "param1": "110",
      "param2": ""
    },
    {
      "voice": "",
      "face": "",
      "select": 0,
      "flag": "",
      "uniq": 6023952,
      "effect": "",
      "param0": "17",
      "place": 0,
      "param3": "",
      "command": 6,
      "param1": "120",
      "param2": ""
    },
    {
      "voice": "",
      "face": "",
      "select": 0,
      "flag": "",
      "uniq": 6023953,
      "effect": "",
      "param0": "",
      "place": 0,
      "param3": "",
      "command": 7,
      "param1": "1",
      "param2": ""
    },
    {
      "voice": "",
      "face": "idle",
      "select": 0,
      "flag": "",
      "uniq": 6023954,
      "effect": "",
      "param0": "18",
      "place": 0,
      "param3": "",
      "command": 2,
      "param1": "1100",
      "param2": ""
    },
    {
      "voice": "",
      "face": "idle",
      "select": 0,
      "flag": "",
      "uniq": 6023955,
      "effect": "",
      "param0": "19",
      "place": 1,
      "param3": "",
      "command": 2,
      "param1": "250",
      "param2": ""
    },
    {
      "voice": "",
      "face": "idle",
      "select": 0,
      "flag": "",
      "uniq": 6023956,
      "effect": "",
      "param0": "20",
      "place": 0,
      "param3": "",
      "command": 2,
      "param1": "1100",
      "param2": ""
    },
    {
      "voice": "",
      "face": "idle",
      "select": 0,
      "flag": "",
      "uniq": 6023957,
      "effect": "",
      "param0": "21",
      "place": 0,
      "param3": "",
      "command": 2,
      "param1": "1100",
      "param2": ""
    },
    {
      "voice": "",
      "face": "idle",
      "select": 0,
      "flag": "",
      "uniq": 6023958,
      "effect": "",
      "param0": "22",
      "place": 0,
      "param3": "",
      "command": 2,
      "param1": "1100",
      "param2": ""
    },
    {
      "voice": "",
      "face": "face_01",
      "select": 0,
      "flag": "",
      "uniq": 6023959,
      "effect": "",
      "param0": "23",
      "place": 1,
      "param3": "",
      "command": 2,
      "param1": "250",
      "param2": ""
    },
    {
      "voice": "",
      "face": "",
      "select": 0,
      "flag": "",
      "uniq": 6023960,
      "effect": "",
      "param0": "24",
      "place": 0,
      "param3": "",
      "command": 6,
      "param1": "210",
      "param2": ""
    },
    {
      "voice": "",
      "face": "",
      "select": 0,
      "flag": "",
      "uniq": 6023961,
      "effect": "",
      "param0": "25",
      "place": 0,
      "param3": "",
      "command": 6,
      "param1": "220",
      "param2": ""
    },
    {
      "voice": "",
      "face": "",
      "select": 0,
      "flag": "",
      "uniq": 6023962,
      "effect": "",
      "param0": "",
      "place": 0,
      "param3": "",
      "command": 7,
      "param1": "2",
      "param2": ""
    },
    {
      "voice": "",
      "face": "idle",
      "select": 0,
      "flag": "",
      "uniq": 6023963,
      "effect": "",
      "param0": "26",
      "place": 0,
      "param3": "",
      "command": 2,
      "param1": "170",
      "param2": ""
    },
    {
      "voice": "",
      "face": "idle",
      "select": 0,
      "flag": "",
      "uniq": 6023964,
      "effect": "",
      "param0": "27",
      "place": 0,
      "param3": "",
      "command": 2,
      "param1": "170",
      "param2": ""
    },
    {
      "voice": "",
      "face": "idle",
      "select": 0,
      "flag": "",
      "uniq": 6023965,
      "effect": "",
      "param0": "28",
      "place": 0,
      "param3": "",
      "command": 2,
      "param1": "170",
      "param2": ""
    },
    {
      "voice": "",
      "face": "idle",
      "select": 0,
      "flag": "",
      "uniq": 6023966,
      "effect": "",
      "param0": "29",
      "place": 0,
      "param3": "",
      "command": 2,
      "param1": "170",
      "param2": ""
    },
    {
      "voice": "",
      "face": "face_01",
      "select": 0,
      "flag": "",
      "uniq": 6023967,
      "effect": "",
      "param0": "30",
      "place": 1,
      "param3": "",
      "command": 2,
      "param1": "250",
      "param2": ""
    },
    {
      "voice": "",
      "face": "",
      "select": 0,
      "flag": "",
      "uniq": 6023968,
      "effect": "",
      "param0": "all",
      "place": 0,
      "param3": "",
      "command": 3,
      "param1": "",
      "param2": ""
    },
    {
      "voice": "",
      "face": "",
      "select": 0,
      "flag": "",
      "uniq": 6023969,
      "effect": "",
      "param0": "",
      "place": 1,
      "param3": "",
      "command": 12,
      "param1": "",
      "param2": ""
    },
    {
      "voice": "",
      "face": "",
      "select": 0,
      "flag": "",
      "uniq": 6023970,
      "effect": "",
      "param0": "bout",
      "place": 0,
      "param3": "",
      "command": 10,
      "param1": "30",
      "param2": ""
    },
    {
      "voice": "",
      "face": "",
      "select": 0,
      "flag": "",
      "uniq": 6023971,
      "effect": "",
      "param0": "bin",
      "place": 0,
      "param3": "",
      "command": 10,
      "param1": "30",
      "param2": ""
    },
    {
      "voice": "",
      "face": "",
      "select": 0,
      "flag": "",
      "uniq": 6023972,
      "effect": "",
      "param0": "31",
      "place": 0,
      "param3": "",
      "command": 4,
      "param1": "",
      "param2": ""
    },
    {
      "voice": "",
      "face": "face_04",
      "select": 0,
      "flag": "",
      "uniq": 6023973,
      "effect": "",
      "param0": "32",
      "place": 0,
      "param3": "",
      "command": 2,
      "param1": "170",
      "param2": ""
    },
    {
      "voice": "",
      "face": "face_04",
      "select": 0,
      "flag": "",
      "uniq": 6023974,
      "effect": "",
      "param0": "33",
      "place": 0,
      "param3": "",
      "command": 2,
      "param1": "170",
      "param2": ""
    },
    {
      "voice": "",
      "face": "",
      "select": 0,
      "flag": "",
      "uniq": 6023975,
      "effect": "",
      "param0": "bgm_drama_unquiet",
      "place": 1,
      "param3": "",
      "command": 12,
      "param1": "",
      "param2": ""
    },
    {
      "voice": "",
      "face": "idle",
      "select": 0,
      "flag": "",
      "uniq": 6023976,
      "effect": "",
      "param0": "34",
      "place": 1,
      "param3": "",
      "command": 2,
      "param1": "1000",
      "param2": ""
    },
    {
      "voice": "",
      "face": "idle",
      "select": 0,
      "flag": "",
      "uniq": 6023977,
      "effect": "",
      "param0": "35",
      "place": 0,
      "param3": "",
      "command": 2,
      "param1": "1100",
      "param2": ""
    },
    {
      "voice": "",
      "face": "idle",
      "select": 0,
      "flag": "",
      "uniq": 6023978,
      "effect": "",
      "param0": "36",
      "place": 1,
      "param3": "",
      "command": 2,
      "param1": "17100",
      "param2": ""
    },
    {
      "voice": "",
      "face": "idle",
      "select": 0,
      "flag": "",
      "uniq": 6023979,
      "effect": "",
      "param0": "37",
      "place": 1,
      "param3": "",
      "command": 2,
      "param1": "17100",
      "param2": ""
    },
    {
      "voice": "",
      "face": "idle",
      "select": 0,
      "flag": "",
      "uniq": 6023980,
      "effect": "",
      "param0": "38",
      "place": 0,
      "param3": "",
      "command": 2,
      "param1": "170",
      "param2": ""
    },
    {
      "voice": "",
      "face": "idle",
      "select": 0,
      "flag": "",
      "uniq": 6023981,
      "effect": "",
      "param0": "39",
      "place": 1,
      "param3": "",
      "command": 2,
      "param1": "250",
      "param2": ""
    },
    {
      "voice": "",
      "face": "idle",
      "select": 0,
      "flag": "",
      "uniq": 6023982,
      "effect": "",
      "param0": "40",
      "place": 0,
      "param3": "",
      "command": 2,
      "param1": "170",
      "param2": ""
    },
    {
      "voice": "",
      "face": "idle",
      "select": 0,
      "flag": "",
      "uniq": 6023983,
      "effect": "",
      "param0": "41",
      "place": 0,
      "param3": "",
      "command": 2,
      "param1": "170",
      "param2": ""
    },
    {
      "voice": "",
      "face": "face_03",
      "select": 0,
      "flag": "",
      "uniq": 6023984,
      "effect": "",
      "param0": "42",
      "place": 0,
      "param3": "",
      "command": 2,
      "param1": "170",
      "param2": ""
    },
    {
      "voice": "",
      "face": "",
      "select": 0,
      "flag": "",
      "uniq": 6023985,
      "effect": "",
      "param0": "eff_drama_dfield_green",
      "place": 0,
      "param3": "",
      "command": 9,
      "param1": "1",
      "param2": ""
    },
    {
      "voice": "",
      "face": "",
      "select": 0,
      "flag": "",
      "uniq": 6023986,
      "effect": "",
      "param0": "parallelize",
      "place": 0,
      "param3": "",
      "command": 13,
      "param1": "",
      "param2": ""
    },
    {
      "voice": "",
      "face": "",
      "select": 0,
      "flag": "",
      "uniq": 6023987,
      "effect": "",
      "param0": "5000",
      "place": 0,
      "param3": "",
      "command": 23,
      "param1": "",
      "param2": ""
    },
    {
      "voice": "",
      "face": "idle",
      "select": 0,
      "flag": "",
      "uniq": 6023988,
      "effect": "",
      "param0": "43",
      "place": 1,
      "param3": "",
      "command": 2,
      "param1": "17100",
      "param2": ""
    },
    {
      "voice": "",
      "face": "face_03",
      "select": 0,
      "flag": "",
      "uniq": 6023989,
      "effect": "",
      "param0": "44",
      "place": 0,
      "param3": "",
      "command": 2,
      "param1": "170",
      "param2": ""
    },
    {
      "voice": "",
      "face": "idle",
      "select": 0,
      "flag": "",
      "uniq": 6023990,
      "effect": "",
      "param0": "45",
      "place": 1,
      "param3": "",
      "command": 2,
      "param1": "17100",
      "param2": ""
    },
    {
      "voice": "",
      "face": "idle",
      "select": 0,
      "flag": "",
      "uniq": 6023991,
      "effect": "",
      "param0": "46",
      "place": 1,
      "param3": "",
      "command": 2,
      "param1": "17100",
      "param2": ""
    },
    {
      "voice": "",
      "face": "idle",
      "select": 0,
      "flag": "",
      "uniq": 6023992,
      "effect": "",
      "param0": "47",
      "place": 0,
      "param3": "",
      "command": 2,
      "param1": "170",
      "param2": ""
    },
    {
      "voice": "",
      "face": "idle",
      "select": 0,
      "flag": "",
      "uniq": 6023993,
      "effect": "",
      "param0": "48",
      "place": 1,
      "param3": "",
      "command": 2,
      "param1": "17100",
      "param2": ""
    },
    {
      "voice": "",
      "face": "",
      "select": 0,
      "flag": "",
      "uniq": 6023994,
      "effect": "",
      "param0": "all",
      "place": 0,
      "param3": "",
      "command": 3,
      "param1": "",
      "param2": ""
    },
    {
      "voice": "",
      "face": "",
      "select": 0,
      "flag": "",
      "uniq": 6023995,
      "effect": "",
      "param0": "",
      "place": 0,
      "param3": "",
      "command": 9,
      "param1": "",
      "param2": ""
    },
    {
      "voice": "",
      "face": "",
      "select": 0,
      "flag": "",
      "uniq": 6023996,
      "effect": "",
      "param0": "",
      "place": 1,
      "param3": "",
      "command": 12,
      "param1": "",
      "param2": ""
    },
    {
      "voice": "",
      "face": "",
      "select": 0,
      "flag": "",
      "uniq": 6023997,
      "effect": "",
      "param0": "bout",
      "place": 0,
      "param3": "",
      "command": 10,
      "param1": "30",
      "param2": ""
    },
    {
      "voice": "",
      "face": "",
      "select": 0,
      "flag": "",
      "uniq": 6023998,
      "effect": "",
      "param0": "bin",
      "place": 0,
      "param3": "",
      "command": 10,
      "param1": "30",
      "param2": ""
    },
    {
      "voice": "",
      "face": "face_04",
      "select": 0,
      "flag": "",
      "uniq": 6023999,
      "effect": "",
      "param0": "49",
      "place": 0,
      "param3": "",
      "command": 2,
      "param1": "170",
      "param2": ""
    },
    {
      "voice": "",
      "face": "",
      "select": 0,
      "flag": "",
      "uniq": 6024000,
      "effect": "",
      "param0": "bgm_drama_search",
      "place": 1,
      "param3": "",
      "command": 12,
      "param1": "",
      "param2": ""
    },
    {
      "voice": "",
      "face": "idle",
      "select": 0,
      "flag": "",
      "uniq": 6024001,
      "effect": "",
      "param0": "50",
      "place": 1,
      "param3": "",
      "command": 2,
      "param1": "17100",
      "param2": ""
    },
    {
      "voice": "",
      "face": "idle",
      "select": 0,
      "flag": "",
      "uniq": 6024002,
      "effect": "",
      "param0": "51",
      "place": 1,
      "param3": "",
      "command": 2,
      "param1": "17100",
      "param2": ""
    },
    {
      "voice": "",
      "face": "face_04",
      "select": 0,
      "flag": "",
      "uniq": 6024003,
      "effect": "",
      "param0": "52",
      "place": 0,
      "param3": "",
      "command": 2,
      "param1": "170",
      "param2": ""
    },
    {
      "voice": "",
      "face": "idle",
      "select": 0,
      "flag": "",
      "uniq": 6024004,
      "effect": "",
      "param0": "53",
      "place": 1,
      "param3": "",
      "command": 2,
      "param1": "17100",
      "param2": ""
    },
    {
      "voice": "",
      "face": "idle",
      "select": 0,
      "flag": "",
      "uniq": 6024005,
      "effect": "",
      "param0": "54",
      "place": 1,
      "param3": "",
      "command": 2,
      "param1": "17100",
      "param2": ""
    },
    {
      "voice": "",
      "face": "face_04",
      "select": 0,
      "flag": "",
      "uniq": 6024006,
      "effect": "",
      "param0": "55",
      "place": 0,
      "param3": "",
      "command": 2,
      "param1": "170",
      "param2": ""
    },
    {
      "voice": "",
      "face": "idle",
      "select": 0,
      "flag": "",
      "uniq": 6024007,
      "effect": "",
      "param0": "56",
      "place": 1,
      "param3": "",
      "command": 2,
      "param1": "17100",
      "param2": ""
    },
    {
      "voice": "",
      "face": "idle",
      "select": 0,
      "flag": "",
      "uniq": 6024008,
      "effect": "",
      "param0": "57",
      "place": 1,
      "param3": "",
      "command": 2,
      "param1": "17100",
      "param2": ""
    },
    {
      "voice": "",
      "face": "idle",
      "select": 0,
      "flag": "",
      "uniq": 6024009,
      "effect": "",
      "param0": "58",
      "place": 1,
      "param3": "",
      "command": 2,
      "param1": "17100",
      "param2": ""
    },
    {
      "voice": "",
      "face": "idle",
      "select": 0,
      "flag": "",
      "uniq": 6024010,
      "effect": "",
      "param0": "59",
      "place": 0,
      "param3": "",
      "command": 2,
      "param1": "120",
      "param2": ""
    },
    {
      "voice": "",
      "face": "idle",
      "select": 0,
      "flag": "",
      "uniq": 6024011,
      "effect": "",
      "param0": "60",
      "place": 1,
      "param3": "",
      "command": 2,
      "param1": "17100",
      "param2": ""
    },
    {
      "voice": "",
      "face": "idle",
      "select": 0,
      "flag": "",
      "uniq": 6024012,
      "effect": "",
      "param0": "61",
      "place": 1,
      "param3": "",
      "command": 2,
      "param1": "17100",
      "param2": ""
    },
    {
      "voice": "",
      "face": "idle",
      "select": 0,
      "flag": "",
      "uniq": 6024013,
      "effect": "",
      "param0": "62",
      "place": 1,
      "param3": "",
      "command": 2,
      "param1": "17100",
      "param2": ""
    },
    {
      "voice": "",
      "face": "face_04",
      "select": 0,
      "flag": "",
      "uniq": 6024014,
      "effect": "",
      "param0": "63",
      "place": 0,
      "param3": "",
      "command": 2,
      "param1": "120",
      "param2": ""
    },
    {
      "voice": "",
      "face": "face_03",
      "select": 0,
      "flag": "",
      "uniq": 6024015,
      "effect": "",
      "param0": "64",
      "place": 1,
      "param3": "",
      "command": 2,
      "param1": "170",
      "param2": ""
    },
    {
      "voice": "",
      "face": "face_03",
      "select": 0,
      "flag": "",
      "uniq": 6024016,
      "effect": "",
      "param0": "65",
      "place": 1,
      "param3": "",
      "command": 2,
      "param1": "170",
      "param2": ""
    },
    {
      "voice": "",
      "face": "face_01",
      "select": 0,
      "flag": "",
      "uniq": 6024017,
      "effect": "",
      "param0": "66",
      "place": 0,
      "param3": "",
      "command": 2,
      "param1": "250",
      "param2": ""
    },
    {
      "voice": "",
      "face": "face_04",
      "select": 0,
      "flag": "",
      "uniq": 6024018,
      "effect": "",
      "param0": "67",
      "place": 1,
      "param3": "",
      "command": 2,
      "param1": "170",
      "param2": ""
    },
    {
      "voice": "",
      "face": "idle",
      "select": 0,
      "flag": "",
      "uniq": 6024019,
      "effect": "",
      "param0": "68",
      "place": 0,
      "param3": "",
      "command": 2,
      "param1": "17100",
      "param2": ""
    },
    {
      "voice": "",
      "face": "idle",
      "select": 0,
      "flag": "",
      "uniq": 6024020,
      "effect": "",
      "param0": "69",
      "place": 0,
      "param3": "",
      "command": 2,
      "param1": "17100",
      "param2": ""
    },
    {
      "voice": "",
      "face": "idle",
      "select": 0,
      "flag": "",
      "uniq": 6024021,
      "effect": "",
      "param0": "70",
      "place": 0,
      "param3": "",
      "command": 2,
      "param1": "17100",
      "param2": ""
    },
    {
      "voice": "",
      "face": "idle",
      "select": 0,
      "flag": "",
      "uniq": 6024022,
      "effect": "",
      "param0": "71",
      "place": 0,
      "param3": "",
      "command": 2,
      "param1": "17100",
      "param2": ""
    },
    {
      "voice": "",
      "face": "idle",
      "select": 0,
      "flag": "",
      "uniq": 6024023,
      "effect": "",
      "param0": "72",
      "place": 0,
      "param3": "",
      "command": 2,
      "param1": "17100",
      "param2": ""
    },
    {
      "voice": "",
      "face": "idle",
      "select": 0,
      "flag": "",
      "uniq": 6024024,
      "effect": "",
      "param0": "73",
      "place": 0,
      "param3": "",
      "command": 2,
      "param1": "17100",
      "param2": ""
    },
    {
      "voice": "",
      "face": "face_04",
      "select": 0,
      "flag": "",
      "uniq": 6024025,
      "effect": "",
      "param0": "74",
      "place": 1,
      "param3": "",
      "command": 2,
      "param1": "170",
      "param2": ""
    },
    {
      "voice": "",
      "face": "idle",
      "select": 0,
      "flag": "",
      "uniq": 6024026,
      "effect": "",
      "param0": "75",
      "place": 0,
      "param3": "",
      "command": 2,
      "param1": "17100",
      "param2": ""
    },
    {
      "voice": "",
      "face": "idle",
      "select": 0,
      "flag": "",
      "uniq": 6024027,
      "effect": "",
      "param0": "76",
      "place": 0,
      "param3": "",
      "command": 2,
      "param1": "17100",
      "param2": ""
    }
  ],
  "charas": [
    {
      "img": "mob_man",
      "id": 1000,
      "name_id": 1000
    },
    {
      "img": "mob_woman",
      "id": 1100,
      "name_id": 1100
    },
    {
      "img": "mob_woman_suit",
      "id": 1305,
      "name_id": 1305
    },
    {
      "img": "rika",
      "id": 120,
      "name_id": 120
    },
    {
      "img": "saikawa",
      "id": 250,
      "name_id": 250
    },
    {
      "img": "gakuto",
      "id": 170,
      "name_id": 170
    },
    {
      "img": "mob_dionysus",
      "id": 17100,
      "name_id": 17100
    }
  ]
}