{
  "transaction_id": "-7-05F-18F85C",
  "server_time": 1697837430807,
  "beginner_mission": {
    "is_badge": false,
    "is_display": false
  },
  "main_mission": {
    "currents": [
      "Clear Story Ch. 1"
    ],
    "is_display": true
  },
  "select_history": [],
  "res_code": 0,
  "client_wait": 0,
  "selects": [],
  "gacha_banner_info": {
    "img": "4800000",
    "end_ts": 1699109999000,
    "limited_days": 14
  },
  "names": [
    {
      "name": "Period",
      "id": 750
    },
    {
      "name": "Alternate Hero",
      "id": 652
    },
    {
      "name": "Demon",
      "id": 28402
    },
    {
      "name": "Alternate Hero",
      "id": 642
    }
  ],
  "texts": [
    {
      "id": 0,
      "text": ">In front of Tupsimati, your fierce battle with Period continues."
    },
    {
      "id": 1,
      "text": ">However, both of your attacks prove ineffective."
    },
    {
      "id": 2,
      "text": "Are you done yet?"
    },
    {
      "id": 3,
      "text": "Ngh! Valkyrie!!"
    },
    {
      "id": 4,
      "text": "*Yell*"
    },
    {
      "id": 5,
      "text": "Get lost."
    },
    {
      "id": 6,
      "text": "!!"
    },
    {
      "id": 7,
      "text": "Aren't you almost out of pawns?"
    },
    {
      "id": 8,
      "text": "We've come this far. We won't die so easily!"
    },
    {
      "id": 9,
      "text": "\"Come this far\"? You just don't get it, do you? You're too late."
    },
    {
      "id": 10,
      "text": "Tupsimati is already booted up. What can you change now?"
    },
    {
      "id": 11,
      "text": "You drone on about your dumbass \"fellowship\" dogma,"
    },
    {
      "id": 12,
      "text": "yet your \"connected\" allies...are nowhere to be seen."
    },
    {
      "id": 13,
      "text": "Oh, maybe they ran away? It's been almost two hours!"
    },
    {
      "id": 14,
      "text": "Are you that afraid of our—of Megakin's—dogma?"
    },
    {
      "id": 15,
      "text": "...\"Afraid\"?"
    },
    {
      "id": 16,
      "text": "Hahahahahaha! You're all so clueless!!"
    },
    {
      "id": 17,
      "text": "I am king of the Mesopotamian gods."
    },
    {
      "id": 18,
      "text": "Our entire pantheon recognized me as such after I killed Tiamat."
    },
    {
      "id": 19,
      "text": "What do I have to fear?"
    },
    {
      "id": 20,
      "text": "I, who refused to tremble before Kingu or any beast."
    },
    {
      "id": 21,
      "text": "I'll tell you the tale of how I was acknowledged by the gods"
    },
    {
      "id": 22,
      "text": "and became Babylon's main deity!"
    },
    {
      "id": 23,
      "text": "Ngh! Valkyrie!!"
    },
    {
      "id": 24,
      "text": "We've come this far. We won't die so easily!"
    },
    {
      "id": 25,
      "text": "Are you that afraid of our—of Megakin's—dogma?"
    }
  ],
  "tm": "8",
  "comeback_mission": {
    "is_badge": false,
    "is_display": false
  },
  "commands": [
    {
      "voice": "",
      "face": "",
      "select": 0,
      "flag": "",
      "uniq": 20031,
      "effect": "",
      "param0": "drama_bg_124.png",
      "place": 0,
      "param3": "",
      "command": 1,
      "param1": "",
      "param2": ""
    },
    {
      "voice": "",
      "face": "",
      "select": 0,
      "flag": "",
      "uniq": 20032,
      "effect": "",
      "param0": "bgm_drama_danger",
      "place": 0,
      "param3": "",
      "command": 12,
      "param1": "",
      "param2": ""
    },
    {
      "voice": "",
      "face": "",
      "select": 0,
      "flag": "",
      "uniq": 20033,
      "effect": "",
      "param0": "0",
      "place": 0,
      "param3": "",
      "command": 4,
      "param1": "",
      "param2": ""
    },
    {
      "voice": "",
      "face": "",
      "select": 0,
      "flag": "",
      "uniq": 20034,
      "effect": "",
      "param0": "1",
      "place": 0,
      "param3": "",
      "command": 4,
      "param1": "",
      "param2": ""
    },
    {
      "voice": "",
      "face": "face_03",
      "select": 0,
      "flag": "",
      "uniq": 20035,
      "effect": "",
      "param0": "2",
      "place": 2,
      "param3": "",
      "command": 2,
      "param1": "750",
      "param2": ""
    },
    {
      "voice": "",
      "face": "",
      "select": 0,
      "flag": "",
      "uniq": 20036,
      "effect": "",
      "param0": "center",
      "place": 0,
      "param3": "",
      "command": 3,
      "param1": "",
      "param2": ""
    },
    {
      "voice": "",
      "face": "",
      "select": 0,
      "flag": "",
      "uniq": 20037,
      "effect": "",
      "param0": "",
      "place": 0,
      "param3": "",
      "command": 28,
      "param1": "",
      "param2": ""
    },
    {
      "voice": "",
      "face": "face_01",
      "select": 1,
      "flag": "",
      "uniq": 20038,
      "effect": "",
      "param0": "3",
      "place": 1,
      "param3": "",
      "command": 2,
      "param1": "652",
      "param2": ""
    },
    {
      "voice": "",
      "face": "idle",
      "select": 1,
      "flag": "",
      "uniq": 20039,
      "effect": "",
      "param0": "4",
      "place": 0,
      "param3": "",
      "command": 2,
      "param1": "28402",
      "param2": ""
    },
    {
      "voice": "",
      "face": "",
      "select": 1,
      "flag": "",
      "uniq": 20040,
      "effect": "",
      "param0": "all",
      "place": 0,
      "param3": "",
      "command": 3,
      "param1": "",
      "param2": ""
    },
    {
      "voice": "",
      "face": "",
      "select": 1,
      "flag": "",
      "uniq": 20041,
      "effect": "",
      "param0": "slash",
      "place": 0,
      "param3": "",
      "command": 13,
      "param1": "",
      "param2": ""
    },
    {
      "voice": "",
      "face": "face_03",
      "select": 1,
      "flag": "",
      "uniq": 20042,
      "effect": "",
      "param0": "5",
      "place": 2,
      "param3": "",
      "command": 2,
      "param1": "750",
      "param2": ""
    },
    {
      "voice": "",
      "face": "",
      "select": 1,
      "flag": "",
      "uniq": 20043,
      "effect": "",
      "param0": "center",
      "place": 0,
      "param3": "",
      "command": 3,
      "param1": "",
      "param2": ""
    },
    {
      "voice": "",
      "face": "",
      "select": 1,
      "flag": "",
      "uniq": 20044,
      "effect": "",
      "param0": "400",
      "place": 0,
      "param3": "",
      "command": 23,
      "param1": "",
      "param2": ""
    },
    {
      "voice": "",
      "face": "",
      "select": 1,
      "flag": "",
      "uniq": 20045,
      "effect": "",
      "param0": "slash",
      "place": 0,
      "param3": "",
      "command": 13,
      "param1": "",
      "param2": ""
    },
    {
      "voice": "",
      "face": "",
      "select": 1,
      "flag": "",
      "uniq": 20046,
      "effect": "",
      "param0": "eff_drama_slash_hit",
      "place": 0,
      "param3": "",
      "command": 9,
      "param1": "",
      "param2": ""
    },
    {
      "voice": "",
      "face": "idle",
      "select": 1,
      "flag": "",
      "uniq": 20047,
      "effect": "",
      "param0": "6",
      "place": 2,
      "param3": "",
      "command": 2,
      "param1": "28402",
      "param2": ""
    },
    {
      "voice": "",
      "face": "",
      "select": 1,
      "flag": "",
      "uniq": 20048,
      "effect": "",
      "param0": "center",
      "place": 0,
      "param3": "",
      "command": 3,
      "param1": "",
      "param2": ""
    },
    {
      "voice": "",
      "face": "face_03",
      "select": 1,
      "flag": "",
      "uniq": 20049,
      "effect": "",
      "param0": "7",
      "place": 0,
      "param3": "",
      "command": 2,
      "param1": "750",
      "param2": ""
    },
    {
      "voice": "",
      "face": "face_01",
      "select": 1,
      "flag": "",
      "uniq": 20050,
      "effect": "",
      "param0": "8",
      "place": 1,
      "param3": "",
      "command": 2,
      "param1": "652",
      "param2": ""
    },
    {
      "voice": "",
      "face": "face_02",
      "select": 1,
      "flag": "",
      "uniq": 20051,
      "effect": "",
      "param0": "9",
      "place": 0,
      "param3": "",
      "command": 2,
      "param1": "750",
      "param2": ""
    },
    {
      "voice": "",
      "face": "face_02",
      "select": 1,
      "flag": "",
      "uniq": 20052,
      "effect": "",
      "param0": "10",
      "place": 0,
      "param3": "",
      "command": 2,
      "param1": "750",
      "param2": ""
    },
    {
      "voice": "",
      "face": "face_02",
      "select": 1,
      "flag": "",
      "uniq": 20053,
      "effect": "",
      "param0": "11",
      "place": 0,
      "param3": "",
      "command": 2,
      "param1": "750",
      "param2": ""
    },
    {
      "voice": "",
      "face": "face_02",
      "select": 1,
      "flag": "",
      "uniq": 20054,
      "effect": "",
      "param0": "12",
      "place": 0,
      "param3": "",
      "command": 2,
      "param1": "750",
      "param2": ""
    },
    {
      "voice": "",
      "face": "face_02",
      "select": 1,
      "flag": "",
      "uniq": 20055,
      "effect": "",
      "param0": "13",
      "place": 0,
      "param3": "",
      "command": 2,
      "param1": "750",
      "param2": ""
    },
    {
      "voice": "",
      "face": "",
      "select": 1,
      "flag": "",
      "uniq": 20056,
      "effect": "",
      "param0": "female_branch_03",
      "place": 0,
      "param3": "",
      "command": 40,
      "param1": "",
      "param2": ""
    },
    {
      "voice": "",
      "face": "face_02",
      "select": 1,
      "flag": "",
      "uniq": 20057,
      "effect": "",
      "param0": "14",
      "place": 1,
      "param3": "",
      "command": 2,
      "param1": "652",
      "param2": ""
    },
    {
      "voice": "",
      "face": "face_01",
      "select": 2,
      "flag": "",
      "uniq": 20058,
      "effect": "",
      "param0": "23",
      "place": 1,
      "param3": "",
      "command": 2,
      "param1": "642",
      "param2": ""
    },
    {
      "voice": "",
      "face": "idle",
      "select": 2,
      "flag": "",
      "uniq": 20059,
      "effect": "",
      "param0": "4",
      "place": 0,
      "param3": "",
      "command": 2,
      "param1": "28402",
      "param2": ""
    },
    {
      "voice": "",
      "face": "",
      "select": 2,
      "flag": "",
      "uniq": 20060,
      "effect": "",
      "param0": "all",
      "place": 0,
      "param3": "",
      "command": 3,
      "param1": "",
      "param2": ""
    },
    {
      "voice": "",
      "face": "",
      "select": 2,
      "flag": "",
      "uniq": 20061,
      "effect": "",
      "param0": "slash",
      "place": 0,
      "param3": "",
      "command": 13,
      "param1": "",
      "param2": ""
    },
    {
      "voice": "",
      "face": "face_03",
      "select": 2,
      "flag": "",
      "uniq": 20062,
      "effect": "",
      "param0": "5",
      "place": 2,
      "param3": "",
      "command": 2,
      "param1": "750",
      "param2": ""
    },
    {
      "voice": "",
      "face": "",
      "select": 2,
      "flag": "",
      "uniq": 20063,
      "effect": "",
      "param0": "center",
      "place": 0,
      "param3": "",
      "command": 3,
      "param1": "",
      "param2": ""
    },
    {
      "voice": "",
      "face": "",
      "select": 2,
      "flag": "",
      "uniq": 20064,
      "effect": "",
      "param0": "400",
      "place": 0,
      "param3": "",
      "command": 23,
      "param1": "",
      "param2": ""
    },
    {
      "voice": "",
      "face": "",
      "select": 2,
      "flag": "",
      "uniq": 20065,
      "effect": "",
      "param0": "slash",
      "place": 0,
      "param3": "",
      "command": 13,
      "param1": "",
      "param2": ""
    },
    {
      "voice": "",
      "face": "",
      "select": 2,
      "flag": "",
      "uniq": 20066,
      "effect": "",
      "param0": "eff_drama_slash_hit",
      "place": 0,
      "param3": "",
      "command": 9,
      "param1": "",
      "param2": ""
    },
    {
      "voice": "",
      "face": "idle",
      "select": 2,
      "flag": "",
      "uniq": 20067,
      "effect": "",
      "param0": "6",
      "place": 2,
      "param3": "",
      "command": 2,
      "param1": "28402",
      "param2": ""
    },
    {
      "voice": "",
      "face": "",
      "select": 2,
      "flag": "",
      "uniq": 20068,
      "effect": "",
      "param0": "center",
      "place": 0,
      "param3": "",
      "command": 3,
      "param1": "",
      "param2": ""
    },
    {
      "voice": "",
      "face": "face_03",
      "select": 2,
      "flag": "",
      "uniq": 20069,
      "effect": "",
      "param0": "7",
      "place": 0,
      "param3": "",
      "command": 2,
      "param1": "750",
      "param2": ""
    },
    {
      "voice": "",
      "face": "face_01",
      "select": 2,
      "flag": "",
      "uniq": 20070,
      "effect": "",
      "param0": "24",
      "place": 1,
      "param3": "",
      "command": 2,
      "param1": "642",
      "param2": ""
    },
    {
      "voice": "",
      "face": "face_02",
      "select": 2,
      "flag": "",
      "uniq": 20071,
      "effect": "",
      "param0": "9",
      "place": 0,
      "param3": "",
      "command": 2,
      "param1": "750",
      "param2": ""
    },
    {
      "voice": "",
      "face": "face_02",
      "select": 2,
      "flag": "",
      "uniq": 20072,
      "effect": "",
      "param0": "10",
      "place": 0,
      "param3": "",
      "command": 2,
      "param1": "750",
      "param2": ""
    },
    {
      "voice": "",
      "face": "face_02",
      "select": 2,
      "flag": "",
      "uniq": 20073,
      "effect": "",
      "param0": "11",
      "place": 0,
      "param3": "",
      "command": 2,
      "param1": "750",
      "param2": ""
    },
    {
      "voice": "",
      "face": "face_02",
      "select": 2,
      "flag": "",
      "uniq": 20074,
      "effect": "",
      "param0": "12",
      "place": 0,
      "param3": "",
      "command": 2,
      "param1": "750",
      "param2": ""
    },
    {
      "voice": "",
      "face": "face_02",
      "select": 2,
      "flag": "",
      "uniq": 20075,
      "effect": "",
      "param0": "13",
      "place": 0,
      "param3": "",
      "command": 2,
      "param1": "750",
      "param2": ""
    },
    {
      "voice": "",
      "face": "",
      "select": 2,
      "flag": "",
      "uniq": 20076,
      "effect": "",
      "param0": "male_branch_03",
      "place": 0,
      "param3": "",
      "command": 40,
      "param1": "",
      "param2": ""
    },
    {
      "voice": "",
      "face": "face_02",
      "select": 2,
      "flag": "",
      "uniq": 20077,
      "effect": "",
      "param0": "25",
      "place": 1,
      "param3": "",
      "command": 2,
      "param1": "642",
      "param2": ""
    },
    {
      "voice": "",
      "face": "face_01",
      "select": 0,
      "flag": "",
      "uniq": 20078,
      "effect": "",
      "param0": "15",
      "place": 0,
      "param3": "",
      "command": 2,
      "param1": "750",
      "param2": ""
    },
    {
      "voice": "",
      "face": "face_03",
      "select": 0,
      "flag": "",
      "uniq": 20079,
      "effect": "",
      "param0": "16",
      "place": 0,
      "param3": "",
      "command": 2,
      "param1": "750",
      "param2": ""
    },
    {
      "voice": "",
      "face": "face_03",
      "select": 0,
      "flag": "",
      "uniq": 20080,
      "effect": "",
      "param0": "17",
      "place": 0,
      "param3": "",
      "command": 2,
      "param1": "750",
      "param2": ""
    },
    {
      "voice": "",
      "face": "face_03",
      "select": 0,
      "flag": "",
      "uniq": 20081,
      "effect": "",
      "param0": "18",
      "place": 0,
      "param3": "",
      "command": 2,
      "param1": "750",
      "param2": ""
    },
    {
      "voice": "",
      "face": "face_03",
      "select": 0,
      "flag": "",
      "uniq": 20082,
      "effect": "",
      "param0": "19",
      "place": 0,
      "param3": "",
      "command": 2,
      "param1": "750",
      "param2": ""
    },
    {
      "voice": "",
      "face": "face_03",
      "select": 0,
      "flag": "",
      "uniq": 20083,
      "effect": "",
      "param0": "20",
      "place": 0,
      "param3": "",
      "command": 2,
      "param1": "750",
      "param2": ""
    },
    {
      "voice": "",
      "face": "",
      "select": 0,
      "flag": "",
      "uniq": 20084,
      "effect": "",
      "param0": "all",
      "place": 0,
      "param3": "",
      "command": 3,
      "param1": "",
      "param2": ""
    },
    {
      "voice": "",
      "face": "",
      "select": 0,
      "flag": "",
      "uniq": 20085,
      "effect": "",
      "param0": "400",
      "place": 0,
      "param3": "",
      "command": 23,
      "param1": "",
      "param2": ""
    },
    {
      "voice": "",
      "face": "face_02",
      "select": 0,
      "flag": "",
      "uniq": 20086,
      "effect": "",
      "param0": "21",
      "place": 2,
      "param3": "",
      "command": 2,
      "param1": "750",
      "param2": ""
    },
    {
      "voice": "",
      "face": "face_02",
      "select": 0,
      "flag": "",
      "uniq": 20087,
      "effect": "",
      "param0": "22",
      "place": 2,
      "param3": "",
      "command": 2,
      "param1": "750",
      "param2": ""
    },
    {
      "voice": "",
      "face": "",
      "select": 0,
      "flag": "",
      "uniq": 20088,
      "effect": "",
      "param0": "eff_drama_encount",
      "place": 0,
      "param3": "",
      "command": 9,
      "param1": "0",
      "param2": ""
    },
    {
      "voice": "",
      "face": "",
      "select": 0,
      "flag": "",
      "uniq": 20089,
      "effect": "",
      "param0": "1200",
      "place": 0,
      "param3": "",
      "command": 23,
      "param1": "",
      "param2": ""
    }
  ],
  "charas": [
    {
      "img": "period",
      "id": 750,
      "name_id": 750
    },
    {
      "img": "female_another",
      "id": 652,
      "name_id": 652
    },
    {
      "img": "mob_valkyrie",
      "id": 28402,
      "name_id": 28402
    },
    {
      "img": "male_another",
      "id": 642,
      "name_id": 642
    }
  ]
}